quart_session/__init__.py
quart_session/sessions.py
quart_session/redis_trio/README.md
quart_session/redis_trio/__init__.py
quart_session/redis_trio/client.py
quart_session/redis_trio/connection.py
quart_session/redis_trio/errors.py
quart_session/redis_trio/serialization.py
Quart_Session-1.0.3.dist-info/LICENSE
Quart_Session-1.0.3.dist-info/METADATA
Quart_Session-1.0.3.dist-info/WHEEL
Quart_Session-1.0.3.dist-info/top_level.txt
Quart_Session-1.0.3.dist-info/RECORD
