Metadata-Version: 2.1
Name: Quart-Session
Version: 1.0.3
Summary: Adds server-side session support to your Quart application
Home-page: https://github.com/sferdi0/quart-session
Author: Sander
Author-email: sander@sanderf.nl
License: BSD
Platform: any
Classifier: Environment :: Web Environment
Classifier: Intended Audience :: Developers
Classifier: License :: OSI Approved :: BSD License
Classifier: Operating System :: OS Independent
Classifier: Programming Language :: Python :: 3
Classifier: Programming Language :: Python :: 3.7
Classifier: Programming Language :: Python :: 3.8
Classifier: Topic :: Internet :: WWW/HTTP :: Dynamic Content
Classifier: Topic :: Software Development :: Libraries :: Python Modules
Requires-Dist: Quart (>=0.10.0)
Provides-Extra: dotenv
Requires-Dist: python-dotenv ; extra == 'dotenv'
Provides-Extra: redis
Requires-Dist: aioredis (>=2.0.0) ; extra == 'redis'
